{
  "annotations": {
    "changelogDate": "20260421231059",
    "readOnly": true
  },
  "applications": ["hostMint"],
  "dto": "mapstruct",
  "fields": [
    {
      "fieldName": "correlationId",
      "fieldType": "String",
      "fieldValidateRules": ["required", "maxlength"],
      "fieldValidateRulesMaxlength": "128"
    },
    {
      "fieldName": "method",
      "fieldType": "HttpMethod",
      "fieldValidateRules": ["required"],
      "fieldValues": "GET,POST,PUT,DELETE,PATCH,HEAD,OPTIONS"
    },
    {
      "fieldName": "path",
      "fieldType": "String",
      "fieldValidateRules": ["required", "maxlength"],
      "fieldValidateRulesMaxlength": "500"
    },
    {
      "fieldName": "statusCode",
      "fieldType": "Integer",
      "fieldValidateRules": ["required", "min", "max"],
      "fieldValidateRulesMax": "599",
      "fieldValidateRulesMin": "100"
    },
    {
      "fieldName": "durationMs",
      "fieldType": "Long",
      "fieldValidateRules": ["required", "min"],
      "fieldValidateRulesMin": "0"
    },
    {
      "fieldName": "principal",
      "fieldType": "String",
      "fieldValidateRules": ["maxlength"],
      "fieldValidateRulesMaxlength": "255"
    },
    {
      "fieldName": "ipAddress",
      "fieldType": "String",
      "fieldValidateRules": ["maxlength"],
      "fieldValidateRulesMaxlength": "64"
    },
    {
      "fieldName": "errorCode",
      "fieldType": "String",
      "fieldValidateRules": ["maxlength"],
      "fieldValidateRulesMaxlength": "120"
    },
    {
      "fieldName": "errorMessage",
      "fieldType": "String",
      "fieldValidateRules": ["maxlength"],
      "fieldValidateRulesMaxlength": "1000"
    },
    {
      "fieldName": "createdAt",
      "fieldType": "Instant"
    }
  ],
  "jpaMetamodelFiltering": true,
  "name": "RequestLog",
  "pagination": "pagination",
  "relationships": [
    {
      "otherEntityField": "login",
      "otherEntityName": "user",
      "relationshipName": "actor",
      "relationshipSide": "left",
      "relationshipType": "many-to-one",
      "relationshipWithBuiltInEntity": true
    },
    {
      "otherEntityField": "projectKey",
      "otherEntityName": "project",
      "relationshipName": "project",
      "relationshipSide": "left",
      "relationshipType": "many-to-one"
    }
  ],
  "searchEngine": "elasticsearch",
  "service": "serviceImpl"
}
